aleksis/apps/ldap/__init__.py
aleksis/apps/ldap/apps.py
aleksis/apps/ldap/locale/.keepdir
aleksis/apps/ldap/locale/ar/LC_MESSAGES/django.mo
aleksis/apps/ldap/locale/ar/LC_MESSAGES/django.po
aleksis/apps/ldap/locale/de_DE/LC_MESSAGES/django.mo
aleksis/apps/ldap/locale/de_DE/LC_MESSAGES/django.po
aleksis/apps/ldap/locale/fr/LC_MESSAGES/django.mo
aleksis/apps/ldap/locale/fr/LC_MESSAGES/django.po
aleksis/apps/ldap/locale/la/LC_MESSAGES/django.mo
aleksis/apps/ldap/locale/la/LC_MESSAGES/django.po
aleksis/apps/ldap/locale/nb_NO/LC_MESSAGES/django.mo
aleksis/apps/ldap/locale/nb_NO/LC_MESSAGES/django.po
aleksis/apps/ldap/locale/ru/LC_MESSAGES/django.mo
aleksis/apps/ldap/locale/ru/LC_MESSAGES/django.po
aleksis/apps/ldap/locale/tr_TR/LC_MESSAGES/django.mo
aleksis/apps/ldap/locale/tr_TR/LC_MESSAGES/django.po
aleksis/apps/ldap/locale/uk/LC_MESSAGES/django.mo
aleksis/apps/ldap/locale/uk/LC_MESSAGES/django.po
aleksis/apps/ldap/management/commands/__init__.py
aleksis/apps/ldap/management/commands/mass_ldap_import.py
aleksis/apps/ldap/migrations/0001_preferences.py
aleksis/apps/ldap/migrations/__init__.py
aleksis/apps/ldap/preferences.py
aleksis/apps/ldap/static/.keepdir
aleksis/apps/ldap/tasks.py
aleksis/apps/ldap/util/ldap.py
aleksis/apps/ldap/util/ldap_password.py
aleksis/apps/ldap/util/ldap_sync.py
aleksis_app_ldap-4.0.0.dist-info/LICENCE.rst
aleksis_app_ldap-4.0.0.dist-info/METADATA
aleksis_app_ldap-4.0.0.dist-info/WHEEL
aleksis_app_ldap-4.0.0.dist-info/entry_points.txt
aleksis_app_ldap-4.0.0.dist-info/RECORD
